wordlepoints/__init__.py
wordlepoints/wordle_stats.py
wordlepoints/wordle_words.txt
wordlepoints-0.0.10.dist-info/LICENSE
wordlepoints-0.0.10.dist-info/METADATA
wordlepoints-0.0.10.dist-info/WHEEL
wordlepoints-0.0.10.dist-info/top_level.txt
wordlepoints-0.0.10.dist-info/RECORD
