Metadata-Version: 2.1
Name: wordlepoints
Version: 0.0.10
Summary: Wordle Stats is a score generator that takes challenging your friends in Wordle to the next level. It provides scores for how good each guess was as well as score boosts for how many rounds it took you to solve the puzzle!
Home-page: https://github.com/tkhenry/wordle_stats
Author: Tom Henry
Author-email: thenry3@nd.edu
License: UNKNOWN
Project-URL: Bug Tracker, https://github.com/tkhenry/wordle_stats/issues
Platform: UNKNOWN
Classifier: Programming Language :: Python :: 3
Classifier: License :: OSI Approved :: MIT License
Classifier: Operating System :: OS Independent
Requires-Python: >=3.6
License-File: LICENSE
